imgsplatter/__init__.py
imgsplatter/__main__.py
imgsplatter/splatter.py
imgsplatter-0.1.1.dist-info/METADATA
imgsplatter-0.1.1.dist-info/WHEEL
imgsplatter-0.1.1.dist-info/RECORD
