Metadata-Version: 2.1
Name: imgsplatter
Version: 0.1.1
Summary: Create randomized wallpapers from your favorite images
License: MIT
Author: DJ Stomp
Author-email: 85457381+DJStompZone@users.noreply.github.com
Requires-Python: >=3.10,<4.0
Classifier: License :: OSI Approved :: MIT License
Classifier: Programming Language :: Python :: 3
Classifier: Programming Language :: Python :: 3.10
Classifier: Programming Language :: Python :: 3.11
Classifier: Programming Language :: Python :: 3.12
Requires-Dist: argparse (>=1.4.0,<2.0.0)
Requires-Dist: pillow (>=10.4.0,<11.0.0)
Requires-Dist: tqdm (>=4.66.5,<5.0.0)
